ut_scrape/__init__.py
ut_scrape/api_models.py
ut_scrape/constants.py
ut_scrape/ut_scrape.py
ut_scrape-0.1.0.dist-info/METADATA
ut_scrape-0.1.0.dist-info/WHEEL
ut_scrape-0.1.0.dist-info/licenses/LICENSE
ut_scrape-0.1.0.dist-info/RECORD
