Metadata-Version: 2.4
Name: ut-scrape
Version: 0.1.0
Summary: Untappd Scraper exposed as Reflex REST API
Author-email: Wardy <wardy3+gitlab@gmail.com>
License: MIT License
License-File: LICENSE
Keywords: beer,scraper,untappd
Classifier: Development Status :: 4 - Beta
Classifier: Intended Audience :: Developers
Classifier: License :: OSI Approved :: MIT License
Classifier: Operating System :: OS Independent
Classifier: Programming Language :: Python :: 3
Classifier: Programming Language :: Python :: 3.13
Classifier: Topic :: Software Development :: Libraries :: Python Modules
Requires-Python: >=3.13
Requires-Dist: reflex>=0.7.6
Requires-Dist: untappd-scraper>=0.6.2
